{
  "packages": {
    "preview_RunIT@latest": {
      "name": "preview_RunIT",
      "version": "1.0.0",
      "description": "Preview HTML files in the browser",
      "main_file": "preview.py",
      "dependencies": [],
      "installed": true,
      "install_path": "packages/preview_RunIT"
    },
    "zen-mode_RunIT@latest": {
      "name": "zen-mode_RunIT",
      "version": "1.0.0",
      "description": "A minimal, focused coding interface that displays one line of code at a time.",
      "main_file": "zen_mode.py",
      "dependencies": [],
      "installed": true,
      "install_path": "packages/zen-mode_RunIT"
    },
    "iloveneans_RunIT@latest": {
      "name": "ilovebeans_RunIT",
      "version": "1.0.0",
      "description": "just shows one word.",
      "main_file": "ilovebeans.py",
      "dependencies": [],
      "installed": true,
      "install_path": "packages/ilovebeans_RunIT"
    },
    "ilovebeans_RunIT": {
      "name": "ilovebeans_RunIT",
      "version": "ilovebeans_RunIT@latest",
      "description": "No description available",
      "repository": "https://github.com/mrDevRussia/RunIT-ilovebeans_RunIT-latest",
      "installed": true,
      "install_path": "packages\\ilovebeans_RunIT"
    }
  },
  "core_tool": {
    "name": "RunIT",
    "version": "1.2.0",
    "last_updated": "2025-08-02 00:03:09"
  }
}